pingpong/__init__.py
pingpong/pingpongthread.py
pingpong/robotstatus.py
pingpong/ai/Cp949ToUniTable.py
pingpong/ai/__init__.py
pingpong/ai/aiderived.py
pingpong/ai/aiutils.py
pingpong/ai/classification.py
pingpong/ai/getwebcam.py
pingpong/ai/voiceprocess.py
pingpong/connection/__init__.py
pingpong/connection/connectionutils.py
pingpong/connection/processprotocol.py
pingpong/connection/rawprotocol.py
pingpong/connection/serialprotocol.py
pingpong/connection/utils.py
pingpong/operations/__init__.py
pingpong/operations/operationderived.py
pingpong/operations/cube/__init__.py
pingpong/operations/cube/cubeoperation.py
pingpong/operations/cube/cubeoperationutils.py
pingpong/operations/ledmatrix/__init__.py
pingpong/operations/ledmatrix/ledmatrixoperation.py
pingpong/operations/ledmatrix/ledmatrixoperationutils.py
pingpong/operations/music/__init__.py
pingpong/operations/music/musicoperation.py
pingpong/operations/music/musicoperationutils.py
pingpong/operations/servo/__init__.py
pingpong/operations/servo/servooperation.py
pingpong/operations/servo/servooperationutils.py
pingpong/operations/stepper/__init__.py
pingpong/operations/stepper/stepperoperation.py
pingpong/operations/stepper/stepperoperationbase.py
pingpong/operations/stepper/stepperoperationutils.py
pingpong/protocols/__init__.py
pingpong/protocols/byteutils.py
pingpong/protocols/cubeprotocol.py
pingpong/protocols/generateprotocol.py
pingpong/protocols/ledmatrixprotocol.py
pingpong/protocols/motorprotocol.py
pingpong/protocols/musicprotocol.py
pingpong/protocols/protocolutils.py
pingpongthread/__init__.py
pingpongthread/pingpongthread.py
pingpongthread/robotstatus.py
pingpongthread/ai/Cp949ToUniTable.py
pingpongthread/ai/__init__.py
pingpongthread/ai/aiderived.py
pingpongthread/ai/aiutils.py
pingpongthread/ai/classification.py
pingpongthread/ai/getwebcam.py
pingpongthread/ai/voiceprocess.py
pingpongthread/connection/__init__.py
pingpongthread/connection/connectionutils.py
pingpongthread-1.1.0.dist-info/METADATA
pingpongthread-1.1.0.dist-info/WHEEL
pingpongthread-1.1.0.dist-info/top_level.txt
pingpongthread-1.1.0.dist-info/RECORD
