Metadata-Version: 2.1
Name: pingpongthread
Version: 1.1.0
Summary: sw동행 핑퐁
Home-page: https://github.com/3x-haust/Python_PingPongThread
Author: 3xhaust
Author-email: s2424@e-mirim.hs.kr
Keywords: 3xhaust,python api,pingpong
Classifier: Programming Language :: Python :: 3
Classifier: License :: OSI Approved :: MIT License
Classifier: Operating System :: OS Independent
Requires-Python: >=3.9
Requires-Dist: absl-py>=2.2.2
Requires-Dist: asttokens>=3.0.0
Requires-Dist: astunparse>=1.6.3
Requires-Dist: certifi>=2025.4.26
Requires-Dist: charset-normalizer>=3.4.2
Requires-Dist: click>=8.1.8
Requires-Dist: contourpy>=1.3.0
Requires-Dist: cycler>=0.12.1
Requires-Dist: decorator>=5.2.1
Requires-Dist: exceptiongroup>=1.3.0
Requires-Dist: executing>=2.2.0
Requires-Dist: flatbuffers>=25.2.10
Requires-Dist: fonttools>=4.58.0
Requires-Dist: future>=1.0.0
Requires-Dist: gast>=0.6.0
Requires-Dist: google-pasta>=0.2.0
Requires-Dist: grpcio>=1.71.0
Requires-Dist: gtts>=2.5.4
Requires-Dist: h5py>=3.13.0
Requires-Dist: idna>=3.10
Requires-Dist: importlib-metadata>=8.7.0
Requires-Dist: importlib-resources>=6.5.2
Requires-Dist: ipython>=8.18.1
Requires-Dist: iso8601>=2.1.0
Requires-Dist: jedi>=0.19.2
Requires-Dist: keras>=3.9.2
Requires-Dist: keyboard>=0.13.5
Requires-Dist: kiwisolver>=1.4.7
Requires-Dist: libclang>=18.1.1
Requires-Dist: markdown>=3.8
Requires-Dist: markdown-it-py>=3.0.0
Requires-Dist: markupsafe>=3.0.2
Requires-Dist: matplotlib>=3.9.4
Requires-Dist: matplotlib-inline>=0.1.7
Requires-Dist: mdurl>=0.1.2
Requires-Dist: ml-dtypes>=0.5.1
Requires-Dist: namex>=0.0.9
Requires-Dist: numpy>=2.0.2
Requires-Dist: opencv-python>=4.11.0.86
Requires-Dist: opt-einsum>=3.4.0
Requires-Dist: optree>=0.15.0
Requires-Dist: packaging>=25.0
Requires-Dist: parso>=0.8.4
Requires-Dist: pexpect>=4.9.0
Requires-Dist: pillow>=11.2.1
Requires-Dist: playsound>=1.3.0
Requires-Dist: prompt-toolkit>=3.0.51
Requires-Dist: protobuf>=5.29.4
Requires-Dist: psutil>=7.0.0
Requires-Dist: ptyprocess>=0.7.0
Requires-Dist: pure-eval>=0.2.3
Requires-Dist: pyaudio>=0.2.14
Requires-Dist: pygments>=2.19.1
Requires-Dist: pyobjc>=11.0
Requires-Dist: pyobjc-core>=11.0
Requires-Dist: pyobjc-framework-accessibility>=11.0
Requires-Dist: pyobjc-framework-accounts>=11.0
Requires-Dist: pyobjc-framework-addressbook>=11.0
Requires-Dist: pyobjc-framework-adservices>=11.0
Requires-Dist: pyobjc-framework-adsupport>=11.0
Requires-Dist: pyobjc-framework-applescriptkit>=11.0
Requires-Dist: pyobjc-framework-applescriptobjc>=11.0
Requires-Dist: pyobjc-framework-applicationservices>=11.0
Requires-Dist: pyobjc-framework-apptrackingtransparency>=11.0
Requires-Dist: pyobjc-framework-audiovideobridging>=11.0
Requires-Dist: pyobjc-framework-authenticationservices>=11.0
Requires-Dist: pyobjc-framework-automaticassessmentconfiguration>=11.0
Requires-Dist: pyobjc-framework-automator>=11.0
Requires-Dist: pyobjc-framework-avfoundation>=11.0
Requires-Dist: pyobjc-framework-avkit>=11.0
Requires-Dist: pyobjc-framework-avrouting>=11.0
Requires-Dist: pyobjc-framework-backgroundassets>=11.0
Requires-Dist: pyobjc-framework-browserenginekit>=11.0
Requires-Dist: pyobjc-framework-businesschat>=11.0
Requires-Dist: pyobjc-framework-calendarstore>=11.0
Requires-Dist: pyobjc-framework-callkit>=11.0
Requires-Dist: pyobjc-framework-carbon>=11.0
Requires-Dist: pyobjc-framework-cfnetwork>=11.0
Requires-Dist: pyobjc-framework-cinematic>=11.0
Requires-Dist: pyobjc-framework-classkit>=11.0
Requires-Dist: pyobjc-framework-cloudkit>=11.0
Requires-Dist: pyobjc-framework-cocoa>=11.0
Requires-Dist: pyobjc-framework-collaboration>=11.0
Requires-Dist: pyobjc-framework-colorsync>=11.0
Requires-Dist: pyobjc-framework-contacts>=11.0
Requires-Dist: pyobjc-framework-contactsui>=11.0
Requires-Dist: pyobjc-framework-coreaudio>=11.0
Requires-Dist: pyobjc-framework-coreaudiokit>=11.0
Requires-Dist: pyobjc-framework-corebluetooth>=11.0
Requires-Dist: pyobjc-framework-coredata>=11.0
Requires-Dist: pyobjc-framework-corehaptics>=11.0
Requires-Dist: pyobjc-framework-corelocation>=11.0
Requires-Dist: pyobjc-framework-coremedia>=11.0
Requires-Dist: pyobjc-framework-coremediaio>=11.0
Requires-Dist: pyobjc-framework-coremidi>=11.0
Requires-Dist: pyobjc-framework-coreml>=11.0
Requires-Dist: pyobjc-framework-coremotion>=11.0
Requires-Dist: pyobjc-framework-coreservices>=11.0
Requires-Dist: pyobjc-framework-corespotlight>=11.0
Requires-Dist: pyobjc-framework-coretext>=11.0
Requires-Dist: pyobjc-framework-corewlan>=11.0
Requires-Dist: pyobjc-framework-cryptotokenkit>=11.0
Requires-Dist: pyobjc-framework-datadetection>=11.0
Requires-Dist: pyobjc-framework-devicecheck>=11.0
Requires-Dist: pyobjc-framework-devicediscoveryextension>=11.0
Requires-Dist: pyobjc-framework-dictionaryservices>=11.0
Requires-Dist: pyobjc-framework-discrecording>=11.0
Requires-Dist: pyobjc-framework-discrecordingui>=11.0
Requires-Dist: pyobjc-framework-diskarbitration>=11.0
Requires-Dist: pyobjc-framework-dvdplayback>=11.0
Requires-Dist: pyobjc-framework-eventkit>=11.0
Requires-Dist: pyobjc-framework-exceptionhandling>=11.0
Requires-Dist: pyobjc-framework-executionpolicy>=11.0
Requires-Dist: pyobjc-framework-extensionkit>=11.0
Requires-Dist: pyobjc-framework-externalaccessory>=11.0
Requires-Dist: pyobjc-framework-fileprovider>=11.0
Requires-Dist: pyobjc-framework-fileproviderui>=11.0
Requires-Dist: pyobjc-framework-findersync>=11.0
Requires-Dist: pyobjc-framework-fsevents>=11.0
Requires-Dist: pyobjc-framework-gamecenter>=11.0
Requires-Dist: pyobjc-framework-gamecontroller>=11.0
Requires-Dist: pyobjc-framework-gamekit>=11.0
Requires-Dist: pyobjc-framework-gameplaykit>=11.0
Requires-Dist: pyobjc-framework-healthkit>=11.0
Requires-Dist: pyobjc-framework-imagecapturecore>=11.0
Requires-Dist: pyobjc-framework-inputmethodkit>=11.0
Requires-Dist: pyobjc-framework-installerplugins>=11.0
Requires-Dist: pyobjc-framework-instantmessage>=11.0
Requires-Dist: pyobjc-framework-intents>=11.0
Requires-Dist: pyobjc-framework-intentsui>=11.0
Requires-Dist: pyobjc-framework-iobluetooth>=11.0
Requires-Dist: pyobjc-framework-iobluetoothui>=11.0
Requires-Dist: pyobjc-framework-iosurface>=11.0
Requires-Dist: pyobjc-framework-ituneslibrary>=11.0
Requires-Dist: pyobjc-framework-kernelmanagement>=11.0
Requires-Dist: pyobjc-framework-latentsemanticmapping>=11.0
Requires-Dist: pyobjc-framework-launchservices>=11.0
Requires-Dist: pyobjc-framework-libdispatch>=11.0
Requires-Dist: pyobjc-framework-libxpc>=11.0
Requires-Dist: pyobjc-framework-linkpresentation>=11.0
Requires-Dist: pyobjc-framework-localauthentication>=11.0
Requires-Dist: pyobjc-framework-localauthenticationembeddedui>=11.0
Requires-Dist: pyobjc-framework-mailkit>=11.0
Requires-Dist: pyobjc-framework-mapkit>=11.0
Requires-Dist: pyobjc-framework-mediaaccessibility>=11.0
Requires-Dist: pyobjc-framework-mediaextension>=11.0
Requires-Dist: pyobjc-framework-medialibrary>=11.0
Requires-Dist: pyobjc-framework-mediaplayer>=11.0
Requires-Dist: pyobjc-framework-mediatoolbox>=11.0
Requires-Dist: pyobjc-framework-metal>=11.0
Requires-Dist: pyobjc-framework-metalfx>=11.0
Requires-Dist: pyobjc-framework-metalkit>=11.0
Requires-Dist: pyobjc-framework-metalperformanceshaders>=11.0
Requires-Dist: pyobjc-framework-metalperformanceshadersgraph>=11.0
Requires-Dist: pyobjc-framework-metrickit>=11.0
Requires-Dist: pyobjc-framework-mlcompute>=11.0
Requires-Dist: pyobjc-framework-modelio>=11.0
Requires-Dist: pyobjc-framework-multipeerconnectivity>=11.0
Requires-Dist: pyobjc-framework-naturallanguage>=11.0
Requires-Dist: pyobjc-framework-netfs>=11.0
Requires-Dist: pyobjc-framework-network>=11.0
Requires-Dist: pyobjc-framework-networkextension>=11.0
Requires-Dist: pyobjc-framework-notificationcenter>=11.0
Requires-Dist: pyobjc-framework-opendirectory>=11.0
Requires-Dist: pyobjc-framework-osakit>=11.0
Requires-Dist: pyobjc-framework-oslog>=11.0
Requires-Dist: pyobjc-framework-passkit>=11.0
Requires-Dist: pyobjc-framework-pencilkit>=11.0
Requires-Dist: pyobjc-framework-phase>=11.0
Requires-Dist: pyobjc-framework-photos>=11.0
Requires-Dist: pyobjc-framework-photosui>=11.0
Requires-Dist: pyobjc-framework-preferencepanes>=11.0
Requires-Dist: pyobjc-framework-pushkit>=11.0
Requires-Dist: pyobjc-framework-quartz>=11.0
Requires-Dist: pyobjc-framework-quicklookthumbnailing>=11.0
Requires-Dist: pyobjc-framework-replaykit>=11.0
Requires-Dist: pyobjc-framework-safariservices>=11.0
Requires-Dist: pyobjc-framework-safetykit>=11.0
Requires-Dist: pyobjc-framework-scenekit>=11.0
Requires-Dist: pyobjc-framework-screencapturekit>=11.0
Requires-Dist: pyobjc-framework-screensaver>=11.0
Requires-Dist: pyobjc-framework-screentime>=11.0
Requires-Dist: pyobjc-framework-scriptingbridge>=11.0
Requires-Dist: pyobjc-framework-searchkit>=11.0
Requires-Dist: pyobjc-framework-security>=11.0
Requires-Dist: pyobjc-framework-securityfoundation>=11.0
Requires-Dist: pyobjc-framework-securityinterface>=11.0
Requires-Dist: pyobjc-framework-sensitivecontentanalysis>=11.0
Requires-Dist: pyobjc-framework-servicemanagement>=11.0
Requires-Dist: pyobjc-framework-sharedwithyou>=11.0
Requires-Dist: pyobjc-framework-sharedwithyoucore>=11.0
Requires-Dist: pyobjc-framework-shazamkit>=11.0
Requires-Dist: pyobjc-framework-social>=11.0
Requires-Dist: pyobjc-framework-soundanalysis>=11.0
Requires-Dist: pyobjc-framework-speech>=11.0
Requires-Dist: pyobjc-framework-spritekit>=11.0
Requires-Dist: pyobjc-framework-storekit>=11.0
Requires-Dist: pyobjc-framework-symbols>=11.0
Requires-Dist: pyobjc-framework-syncservices>=11.0
Requires-Dist: pyobjc-framework-systemconfiguration>=11.0
Requires-Dist: pyobjc-framework-systemextensions>=11.0
Requires-Dist: pyobjc-framework-threadnetwork>=11.0
Requires-Dist: pyobjc-framework-uniformtypeidentifiers>=11.0
Requires-Dist: pyobjc-framework-usernotifications>=11.0
Requires-Dist: pyobjc-framework-usernotificationsui>=11.0
Requires-Dist: pyobjc-framework-videosubscriberaccount>=11.0
Requires-Dist: pyobjc-framework-videotoolbox>=11.0
Requires-Dist: pyobjc-framework-virtualization>=11.0
Requires-Dist: pyobjc-framework-vision>=11.0
Requires-Dist: pyobjc-framework-webkit>=11.0
Requires-Dist: pyparsing>=3.2.3
Requires-Dist: pyserial>=3.5
Requires-Dist: python-dateutil>=2.9.0.post0
Requires-Dist: pyyaml>=6.0.2
Requires-Dist: requests>=2.32.3
Requires-Dist: rich>=14.0.0
Requires-Dist: six>=1.17.0
Requires-Dist: speechrecognition>=3.14.2
Requires-Dist: stack-data>=0.6.3
Requires-Dist: tensorboard>=2.19.0
Requires-Dist: tensorboard-data-server>=0.7.2
Requires-Dist: tensorflow>=2.19.0
Requires-Dist: tensorflow-io-gcs-filesystem>=0.37.1
Requires-Dist: termcolor>=3.1.0
Requires-Dist: traitlets>=5.14.3
Requires-Dist: typing-extensions>=4.13.2
Requires-Dist: urllib3>=2.4.0
Requires-Dist: wcwidth>=0.2.13
Requires-Dist: werkzeug>=3.1.3
Requires-Dist: wrapt>=1.17.2
Requires-Dist: zipp>=3.21.0
